{
  "id": "conic-sections",
  "title": "Conic Sections",
  "subject": "Mathematics",
  "chapter": "Coordinate Geometry",
  "content": "# Coordinate Geometry: Conics (Parabola, Ellipse, Hyperbola)\n\n## 1. Parabola ($e=1$)\n### 1.1 Standard Equations\n- $y^2 = 4ax$: Focus $(a, 0)$, Directrix $x = -a$, LR length $4a$.\n- **Parametric Form:** $(at^2, 2at)$.\n- **Tangent (Slope $m$):** $y = mx + a/m$.\n- **Normal (Slope $m$):** $y = mx - 2am - am^3$.\n\n### 1.2 Key Properties\n- **Focal Chord:** If $(at_1^2, 2at_1)$ and $(at_2^2, 2at_2)$ are ends of a focal chord, then $t_1 t_2 = -1$.\n- **Reflection:** Rays from focus reflect parallel to the axis.\n\n## 2. Ellipse ($e < 1$)\n### 2.1 Standard Equations\n- $\\frac{x^2}{a^2} + \\frac{y^2}{b^2} = 1$: $b^2 = a^2(1-e^2)$. Foci $(\\pm ae, 0)$.\n- **Parametric Form:** $(a \\cos \\theta, b \\sin \\theta)$.\n- **Tangent (Slope $m$):** $y = mx \\pm \\sqrt{a^2m^2 + b^2}$.\n- **Normal (at $\\theta$):** $\\frac{ax}{\\cos \\theta} - \\frac{by}{\\sin \\theta} = a^2 - b^2$.\n\n### 2.2 Key Properties\n- **Focal Property:** $PS_1 + PS_2 = 2a$ (sum of distances from foci is constant).\n- **Director Circle:** $x^2 + y^2 = a^2 + b^2$.\n\n## 3. Hyperbola ($e > 1$)\n### 3.1 Standard Equations\n- $\\frac{x^2}{a^2} - \\frac{y^2}{b^2} = 1$: $b^2 = a^2(e^2-1)$. Foci $(\\pm ae, 0)$.\n- **Conjugate Hyperbola:** $-\\frac{x^2}{a^2} + \\frac{y^2}{b^2} = 1$.\n- **Rectangular Hyperbola ($e = \\sqrt{2}$):** $x^2 - y^2 = a^2$ OR $xy = c^2$.\n\n### 3.2 Tangents & Asymptotes\n- **Tangent (Slope $m$):** $y = mx \\pm \\sqrt{a^2m^2 - b^2}$.\n- **Asymptotes:** $y = \\pm \\frac{b}{a} x$. The angle between them is $2\\tan^{-1}(b/a)$.\n\n## 4. Visual Aids & Diagrams\n*(Imagine a cone being sliced at different angles: a parallel slice is a circle, a tilted slice is an ellipse, a slice parallel to the side is a parabola, and a steep vertical slice is a hyperbola. Visualize the \"focal property\" of an ellipse as a gardener drawing a circle with two stakes and a loose loop of string. For hyperbola, see the curve approaching its asymptotes but never touching them.)*\n\n## Typed Problems (JEE Main PYQ Based)\n\n### Type 1: Tangent to Parabola\n**Q1.** Find the equation of common tangent to $y^2 = 4x$ and $x^2 = 32y$.\n**Concept:** $y = mx + 1/m$ must also touch $x^2 = 32y$.\n**Solution:**\n1. Tangent to $y^2=4x$ is $y = mx + 1/m$.\n2. Sub into $x^2 = 32y$: $x^2 = 32(mx + 1/m) \\Rightarrow x^2 - 32mx - 32/m = 0$.\n3. For tangency, $D = 0 \\Rightarrow (32m)^2 - 4(1)(-32/m) = 0$.\n4. $32^2 m^2 + 128/m = 0 \\Rightarrow 1024 m^3 + 128 = 0 \\Rightarrow m^3 = -1/8 \\Rightarrow m = -1/2$.\n5. Tangent: $y = -x/2 - 2 \\Rightarrow x + 2y + 4 = 0$.\n\n### Type 2: Eccentricity of Hyperbola\n**Q1.** If the latus rectum of a hyperbola is half of its transverse axis, find its eccentricity.\n**Concept:** $2b^2/a = a \\Rightarrow 2b^2 = a^2$.\n**Solution:**\n1. $b^2 = a^2(e^2-1) \\Rightarrow a^2/2 = a^2(e^2-1)$.\n2. $1/2 = e^2 - 1 \\Rightarrow e^2 = 3/2 \\Rightarrow e = \\sqrt{3/2}$.\n\n### Type 3: Area of Triangle (Coordinate Geometry)\n**Q1.** Find the area of the triangle formed by the tangent to $x^2/a^2 + y^2/b^2 = 1$ at $(a \\cos \\theta, b \\sin \\theta)$ with the coordinate axes.\n**Concept:** Tangent is $x \\cos \\theta / a + y \\sin \\theta / b = 1$.\n**Solution:**\n1. X-intercept: $x = a / \\cos \\theta$. Y-intercept: $y = b / \\sin \\theta$.\n2. Area $= 1/2 |xy| = 1/2 |ab / (\\sin \\theta \\cos \\theta)| = |ab / \\sin 2\\theta|$.\n3. Min area is $ab$ when $\\theta = 45^circ$.\n",
  "lastUpdated": "2026-05-17T23:25:00Z",
  "sources": [
    "https://jeemain.nta.nic.in",
    "https://jeeadv.ac.in"
  ],
  "order": 11
}